bina/__init__.py
bina/camera.py
bina-0.1.2.dist-info/WHEEL
bina-0.1.2.dist-info/METADATA
bina-0.1.2.dist-info/RECORD
