Metadata-Version: 2.1
Name: bina
Version: 0.1.2
Summary: Python Multi-Camera Recording and Synchronization
Home-page: https://github.com/amirivojdan/bina
License: MIT
Keywords: camera,multi-camera,offline synchronization
Author: Ahmad Amirivojdan
Author-email: aamirivo@vols.utk.edu
Requires-Python: >=3.10,<4.0
Classifier: License :: OSI Approved :: MIT License
Classifier: Programming Language :: Python :: 3
Classifier: Programming Language :: Python :: 3.10
Requires-Dist: numpy (>=1.23.3,<2.0.0)
Requires-Dist: opencv-python (>=4.6.0.66,<5.0.0.0)
Requires-Dist: pendulum (>=2.1,<3.0)
Project-URL: Author's Home Page, https://amirivojdan.io/
Project-URL: Repository, https://github.com/amirivojdan/bina
